{
  "@context": "http://iiif.io/api/presentation/2/context.json",
  "@id": "https://mejackreed.github.io/parker-scale-data/ft757ht3699/annos/canvas-170.json",
  "@type": "sc:AnnotationList",
  "resources": [
    {
      "@id": "6a23c62414682c6c5a81671124236d82",
      "@type": "oa:Annotation",
      "motivation": "sc:painting",
      "resource": {
        "@id": "02eee88b535e6ff0263599e63194a7bd",
        "@type": "cnt:ContentAsText",
        "format": "text/plain",
        "chars": "Hello!",
        "language": "eng"
      },
      "on": "https://dms-data.stanford.edu/Parker/ft757ht3699/canvas/canvas-170#xywh=0,0,300,300"
    }
  ]
}