{
  "@context": "http://iiif.io/api/presentation/2/context.json",
  "@id": "https://mejackreed.github.io/parker-scale-data/gb770gh4320/annos/canvas-262.json",
  "@type": "sc:AnnotationList",
  "resources": [
    {
      "@id": "3bccaa1963d47872e40f06cda7d20c84",
      "@type": "oa:Annotation",
      "motivation": "sc:painting",
      "resource": {
        "@id": "b8619d3a9405d2f3992651ecbc310d2f",
        "@type": "cnt:ContentAsText",
        "format": "text/plain",
        "chars": "Hello!",
        "language": "eng"
      },
      "on": "http://dms-data.stanford.edu/Parker/gb770gh4320/canvas/canvas-262#xywh=0,0,300,300"
    }
  ]
}