{
  "@context": "http://iiif.io/api/presentation/2/context.json",
  "@id": "https://mejackreed.github.io/parker-scale-data/zy353np1659/annos/canvas-58.json",
  "@type": "sc:AnnotationList",
  "resources": [
    {
      "@id": "c70d10f2bc48f72cf8a258c93f35d8d0",
      "@type": "oa:Annotation",
      "motivation": "sc:painting",
      "resource": {
        "@id": "5ac0994d02e6a50e1b34b1d69f512d8b",
        "@type": "cnt:ContentAsText",
        "format": "text/plain",
        "chars": "Hello!",
        "language": "eng"
      },
      "on": "http://dms-data.stanford.edu/Parker/zy353np1659/canvas/canvas-58#xywh=0,0,300,300"
    }
  ]
}