{
  "@context": "http://iiif.io/api/presentation/2/context.json",
  "@id": "https://mejackreed.github.io/parker-scale-data/bg021sq9590/annos/canvas-166.json",
  "@type": "sc:AnnotationList",
  "resources": [
    {
      "@id": "c59dcf5342a9bfeea65a0b7010fe4ee7",
      "@type": "oa:Annotation",
      "motivation": "sc:painting",
      "resource": {
        "@id": "b89da9e8ec33fd8b4bbd9a99752b8782",
        "@type": "cnt:ContentAsText",
        "format": "text/plain",
        "chars": "Hello!",
        "language": "eng"
      },
      "on": "https://dms-data.stanford.edu/data/manifests/Parker/bg021sq9590/canvas/canvas-166"
    }
  ]
}