{
  "@context": "http://iiif.io/api/presentation/2/context.json",
  "@id": "https://mejackreed.github.io/parker-scale-data/wk321dt4676/annos/canvas-269.json",
  "@type": "sc:AnnotationList",
  "resources": [
    {
      "@id": "3573f746399601b6428520da3491c749",
      "@type": "oa:Annotation",
      "motivation": "sc:painting",
      "resource": {
        "@id": "3ac9979be87c6f5673d0f01f16ee4369",
        "@type": "cnt:ContentAsText",
        "format": "text/plain",
        "chars": "Hello!",
        "language": "eng"
      },
      "on": "http://dms-data.stanford.edu/Parker/wk321dt4676/canvas/canvas-268#xywh=0,0,300,300"
    }
  ]
}