{
  "@context": "http://iiif.io/api/presentation/2/context.json",
  "@id": "https://mejackreed.github.io/parker-scale-data/qy662bj1544/annos/canvas-634.json",
  "@type": "sc:AnnotationList",
  "resources": [
    {
      "@id": "3472856c0dc50c7886685f898d3847f1",
      "@type": "oa:Annotation",
      "motivation": "sc:painting",
      "resource": {
        "@id": "899621f5dcf2a4380355a05337973da5",
        "@type": "cnt:ContentAsText",
        "format": "text/plain",
        "chars": "Hello!",
        "language": "eng"
      },
      "on": "http://dms-data.stanford.edu/Parker/qy662bj1544/canvas/canvas-634#xywh=0,0,300,300"
    }
  ]
}