{
  "@context": "http://iiif.io/api/presentation/2/context.json",
  "@id": "https://mejackreed.github.io/parker-scale-data/qy662bj1544/annos/canvas-817.json",
  "@type": "sc:AnnotationList",
  "resources": [
    {
      "@id": "62d90175b69c18f21196dde9d6f947dd",
      "@type": "oa:Annotation",
      "motivation": "sc:painting",
      "resource": {
        "@id": "e46e5d3fea70b7aec479e6bfb78a9ca8",
        "@type": "cnt:ContentAsText",
        "format": "text/plain",
        "chars": "Hello!",
        "language": "eng"
      },
      "on": "http://dms-data.stanford.edu/Parker/qy662bj1544/canvas/canvas-817#xywh=0,0,300,300"
    }
  ]
}