{
  "@context": "http://iiif.io/api/presentation/2/context.json",
  "@id": "https://mejackreed.github.io/parker-scale-data/pr262rj5610/annos/canvas-44.json",
  "@type": "sc:AnnotationList",
  "resources": [
    {
      "@id": "cb37edb13a2e301b55b273aa7cf9d9db",
      "@type": "oa:Annotation",
      "motivation": "sc:painting",
      "resource": {
        "@id": "4170d585e23a5c31624b9a1c3a0dce9b",
        "@type": "cnt:ContentAsText",
        "format": "text/plain",
        "chars": "Hello!",
        "language": "eng"
      },
      "on": "http://dms-data.stanford.edu/Parker/pr262rj5610/canvas/canvas-44#xywh=0,0,300,300"
    }
  ]
}