{
  "@context": "http://iiif.io/api/presentation/2/context.json",
  "@id": "https://mejackreed.github.io/parker-scale-data/xd669dx1412/annos/canvas-234.json",
  "@type": "sc:AnnotationList",
  "resources": [
    {
      "@id": "51dfb09bf1df5f90860d5ea4e73a74bf",
      "@type": "oa:Annotation",
      "motivation": "sc:painting",
      "resource": {
        "@id": "447ef52449c23f0733ef158730a7218a",
        "@type": "cnt:ContentAsText",
        "format": "text/plain",
        "chars": "Hello!",
        "language": "eng"
      },
      "on": "http://dms-data.stanford.edu/Parker/xd669dx1412/canvas/canvas-234#xywh=0,0,300,300"
    }
  ]
}