{
  "@context": "http://iiif.io/api/presentation/2/context.json",
  "@id": "https://mejackreed.github.io/parker-scale-data/xc573pw8032/annos/canvas-382.json",
  "@type": "sc:AnnotationList",
  "resources": [
    {
      "@id": "cb8296e4f552858e1660ff8081028de1",
      "@type": "oa:Annotation",
      "motivation": "sc:painting",
      "resource": {
        "@id": "a127dd12af6da6c8760f10fd26c53e99",
        "@type": "cnt:ContentAsText",
        "format": "text/plain",
        "chars": "Hello!",
        "language": "eng"
      },
      "on": "http://dms-data.stanford.edu/Parker/xc573pw8032/canvas/canvas-382#xywh=0,0,300,300"
    }
  ]
}