{
  "@context": "http://iiif.io/api/presentation/2/context.json",
  "@id": "https://mejackreed.github.io/parker-scale-data/dm833zd9241/annos/canvas-44.json",
  "@type": "sc:AnnotationList",
  "resources": [
    {
      "@id": "30a6122c98ee5cf3d42f8fa23a1fe4f9",
      "@type": "oa:Annotation",
      "motivation": "sc:painting",
      "resource": {
        "@id": "499ef2edc3421d14b3192ece699fc304",
        "@type": "cnt:ContentAsText",
        "format": "text/plain",
        "chars": "Hello!",
        "language": "eng"
      },
      "on": "http://dms-data.stanford.edu/Parker/dm833zd9241/canvas/canvas-44#xywh=0,0,300,300"
    }
  ]
}