{
  "@context": "http://iiif.io/api/presentation/2/context.json",
  "@id": "https://mejackreed.github.io/parker-scale-data/gf842rx6366/annos/canvas-324.json",
  "@type": "sc:AnnotationList",
  "resources": [
    {
      "@id": "4a3be8e5473c3687c5e81b73cb41f7f0",
      "@type": "oa:Annotation",
      "motivation": "sc:painting",
      "resource": {
        "@id": "588311bf908e325e870a5dad499fb9f6",
        "@type": "cnt:ContentAsText",
        "format": "text/plain",
        "chars": "Hello!",
        "language": "eng"
      },
      "on": "http://dms-data.stanford.edu/Parker/gf842rx6366/canvas/canvas-324#xywh=0,0,300,300"
    }
  ]
}