{
  "@context": "http://iiif.io/api/presentation/2/context.json",
  "@id": "https://mejackreed.github.io/parker-scale-data/gf842rx6366/annos/canvas-46.json",
  "@type": "sc:AnnotationList",
  "resources": [
    {
      "@id": "903a00f522bb029cab41e6d7be48188b",
      "@type": "oa:Annotation",
      "motivation": "sc:painting",
      "resource": {
        "@id": "2b0acd46a2229be30797f64ea5e0b88c",
        "@type": "cnt:ContentAsText",
        "format": "text/plain",
        "chars": "Hello!",
        "language": "eng"
      },
      "on": "http://dms-data.stanford.edu/Parker/gf842rx6366/canvas/canvas-46#xywh=0,0,300,300"
    }
  ]
}