{
  "@context": "http://iiif.io/api/presentation/2/context.json",
  "@id": "https://mejackreed.github.io/parker-scale-data/qv517bq6409/annos/canvas-71.json",
  "@type": "sc:AnnotationList",
  "resources": [
    {
      "@id": "9ad0d152bc46575cfb16bf96961f481d",
      "@type": "oa:Annotation",
      "motivation": "sc:painting",
      "resource": {
        "@id": "4ab4e03284b62b83ed2b42f27fe731bb",
        "@type": "cnt:ContentAsText",
        "format": "text/plain",
        "chars": "Hello!",
        "language": "eng"
      },
      "on": "http://dms-data.stanford.edu/Parker/qv517bq6409/canvas/canvas-71#xywh=0,0,300,300"
    }
  ]
}