{
  "@context": "http://iiif.io/api/presentation/2/context.json",
  "@id": "https://mejackreed.github.io/parker-scale-data/jy445fd9276/annos/canvas-46.json",
  "@type": "sc:AnnotationList",
  "resources": [
    {
      "@id": "0aaf5012e30691bc6d7157cb43c4dcd6",
      "@type": "oa:Annotation",
      "motivation": "sc:painting",
      "resource": {
        "@id": "df8e2936935eb95c829293a35dc0ee61",
        "@type": "cnt:ContentAsText",
        "format": "text/plain",
        "chars": "Hello!",
        "language": "eng"
      },
      "on": "http://dms-data.stanford.edu/Parker/jy445fd9276/canvas/canvas-46#xywh=0,0,300,300"
    }
  ]
}