{
  "@context": "http://iiif.io/api/presentation/2/context.json",
  "@id": "https://mejackreed.github.io/parker-scale-data/jy445fd9276/annos/canvas-155.json",
  "@type": "sc:AnnotationList",
  "resources": [
    {
      "@id": "9966e51d5c3018a3f71a0f72af592650",
      "@type": "oa:Annotation",
      "motivation": "sc:painting",
      "resource": {
        "@id": "a17a88005d43bf2dc82c9db78fda84f9",
        "@type": "cnt:ContentAsText",
        "format": "text/plain",
        "chars": "Hello!",
        "language": "eng"
      },
      "on": "http://dms-data.stanford.edu/Parker/jy445fd9276/canvas/canvas-155#xywh=0,0,300,300"
    }
  ]
}