{
  "@context": "http://iiif.io/api/presentation/2/context.json",
  "@id": "https://mejackreed.github.io/parker-scale-data/nm956yw8777/annos/canvas-69.json",
  "@type": "sc:AnnotationList",
  "resources": [
    {
      "@id": "d6bbc7ff179f300b4103f26bdd7e99dc",
      "@type": "oa:Annotation",
      "motivation": "sc:painting",
      "resource": {
        "@id": "5eb9746342212cd1ca8daf6a89b09a68",
        "@type": "cnt:ContentAsText",
        "format": "text/plain",
        "chars": "Hello!",
        "language": "eng"
      },
      "on": "http://dms-data.stanford.edu/Parker/nm956yw8777/canvas/canvas-69#xywh=0,0,300,300"
    }
  ]
}