{
  "@context": "http://iiif.io/api/presentation/2/context.json",
  "@id": "https://mejackreed.github.io/parker-scale-data/yw585wy1264/annos/canvas-374.json",
  "@type": "sc:AnnotationList",
  "resources": [
    {
      "@id": "db6c2195ae99e1295c7dfe4199c44b42",
      "@type": "oa:Annotation",
      "motivation": "sc:painting",
      "resource": {
        "@id": "9086ced4a80a00a7ef20a1ab906b5771",
        "@type": "cnt:ContentAsText",
        "format": "text/plain",
        "chars": "Hello!",
        "language": "eng"
      },
      "on": "http://dms-data.stanford.edu/Parker/yw585wy1264/canvas/canvas-374#xywh=0,0,300,300"
    }
  ]
}