{
  "@context": "http://iiif.io/api/presentation/2/context.json",
  "@id": "https://mejackreed.github.io/parker-scale-data/hj164fb1760/annos/canvas-243.json",
  "@type": "sc:AnnotationList",
  "resources": [
    {
      "@id": "d1930945182dd0b0f000d425344807c1",
      "@type": "oa:Annotation",
      "motivation": "sc:painting",
      "resource": {
        "@id": "33d9a6aee01163c2c12a2df60cb623df",
        "@type": "cnt:ContentAsText",
        "format": "text/plain",
        "chars": "Hello!",
        "language": "eng"
      },
      "on": "http://dms-data.stanford.edu/Parker/hj164fb1760/canvas/canvas-243#xywh=0,0,300,300"
    }
  ]
}