{
  "@context": "http://iiif.io/api/presentation/2/context.json",
  "@id": "https://mejackreed.github.io/parker-scale-data/gz764sr2328/annos/canvas-280.json",
  "@type": "sc:AnnotationList",
  "resources": [
    {
      "@id": "8cf7fe3dc675aa035a48962d72e73741",
      "@type": "oa:Annotation",
      "motivation": "sc:painting",
      "resource": {
        "@id": "aebbdf0872a42305cd99b47c26c423cd",
        "@type": "cnt:ContentAsText",
        "format": "text/plain",
        "chars": "Hello!",
        "language": "eng"
      },
      "on": "http://dms-data.stanford.edu/Parker/gz764sr2328/canvas/canvas-280#xywh=0,0,300,300"
    }
  ]
}