{
  "@context": "http://iiif.io/api/presentation/2/context.json",
  "@id": "https://mejackreed.github.io/parker-scale-data/gz764sr2328/annos/canvas-879.json",
  "@type": "sc:AnnotationList",
  "resources": [
    {
      "@id": "ebba1b441e808d66c2a94fd946fb3c64",
      "@type": "oa:Annotation",
      "motivation": "sc:painting",
      "resource": {
        "@id": "21b7810e36a4760a6e4466d874d06671",
        "@type": "cnt:ContentAsText",
        "format": "text/plain",
        "chars": "Hello!",
        "language": "eng"
      },
      "on": "http://dms-data.stanford.edu/Parker/gz764sr2328/canvas/canvas-879#xywh=0,0,300,300"
    }
  ]
}