{
  "@context": "http://iiif.io/api/presentation/2/context.json",
  "@id": "https://mejackreed.github.io/parker-scale-data/zh479gp8621/annos/canvas-136.json",
  "@type": "sc:AnnotationList",
  "resources": [
    {
      "@id": "609ece9164cf5c48526e013254bef138",
      "@type": "oa:Annotation",
      "motivation": "sc:painting",
      "resource": {
        "@id": "92263ce7720b97c0845a758fb4241aa4",
        "@type": "cnt:ContentAsText",
        "format": "text/plain",
        "chars": "Hello!",
        "language": "eng"
      },
      "on": "http://dms-data.stanford.edu/Parker/zh479gp8621/canvas/canvas-136#xywh=0,0,300,300"
    }
  ]
}