{
  "@context": "http://iiif.io/api/presentation/2/context.json",
  "@id": "https://mejackreed.github.io/parker-scale-data/bh709gt4292/annos/canvas-133.json",
  "@type": "sc:AnnotationList",
  "resources": [
    {
      "@id": "b93a0bdf8c4343c8639253ab59315623",
      "@type": "oa:Annotation",
      "motivation": "sc:painting",
      "resource": {
        "@id": "393db144f26cb29a0bda2943d295e24b",
        "@type": "cnt:ContentAsText",
        "format": "text/plain",
        "chars": "Hello!",
        "language": "eng"
      },
      "on": "http://dms-data.stanford.edu/Parker/bh709gt4292/canvas/canvas-133"
    }
  ]
}