{
  "@context": "http://iiif.io/api/presentation/2/context.json",
  "@id": "https://mejackreed.github.io/parker-scale-data/cn679rn6130/annos/canvas-138.json",
  "@type": "sc:AnnotationList",
  "resources": [
    {
      "@id": "129e30240f630306e6d682743d786334",
      "@type": "oa:Annotation",
      "motivation": "sc:painting",
      "resource": {
        "@id": "12452bc283a3cb7fcd418a3c9fe6b4a4",
        "@type": "cnt:ContentAsText",
        "format": "text/plain",
        "chars": "Hello!",
        "language": "eng"
      },
      "on": "http://dms-data.stanford.edu/Parker/cn679rn6130/canvas/canvas-138#xywh=0,0,300,300"
    }
  ]
}