{
  "@context": "http://iiif.io/api/presentation/2/context.json",
  "@id": "https://mejackreed.github.io/parker-scale-data/mj866ts0420/annos/canvas-409.json",
  "@type": "sc:AnnotationList",
  "resources": [
    {
      "@id": "b03ebfc05d2167ebe1e12f83194445d7",
      "@type": "oa:Annotation",
      "motivation": "sc:painting",
      "resource": {
        "@id": "e0ab057b836f9d3c41a2c1a3a11d148c",
        "@type": "cnt:ContentAsText",
        "format": "text/plain",
        "chars": "Hello!",
        "language": "eng"
      },
      "on": "http://dms-data.stanford.edu/Parker/mj866ts0420/canvas/canvas-409#xywh=0,0,300,300"
    }
  ]
}