{
  "@context": "http://iiif.io/api/presentation/2/context.json",
  "@id": "https://mejackreed.github.io/parker-scale-data/cy895rg0439/annos/canvas-288.json",
  "@type": "sc:AnnotationList",
  "resources": [
    {
      "@id": "f1f27c01172e3167fae933d21850f731",
      "@type": "oa:Annotation",
      "motivation": "sc:painting",
      "resource": {
        "@id": "0002c43e1a439c6afa72af42a9d3f7df",
        "@type": "cnt:ContentAsText",
        "format": "text/plain",
        "chars": "Hello!",
        "language": "eng"
      },
      "on": "http://dms-data.stanford.edu/Parker/cy895rg0439/canvas/canvas-288#xywh=0,0,300,300"
    }
  ]
}