{
  "@context": "http://iiif.io/api/presentation/2/context.json",
  "@id": "https://mejackreed.github.io/parker-scale-data/vy908wk5791/annos/canvas-148.json",
  "@type": "sc:AnnotationList",
  "resources": [
    {
      "@id": "64b753188440ba32416c4f8a03e5b29c",
      "@type": "oa:Annotation",
      "motivation": "sc:painting",
      "resource": {
        "@id": "522edabb617764d28af88334af72bb47",
        "@type": "cnt:ContentAsText",
        "format": "text/plain",
        "chars": "Hello!",
        "language": "eng"
      },
      "on": "http://dms-data.stanford.edu/Parker/vy908wk5791/canvas/canvas-148#xywh=0,0,300,300"
    }
  ]
}