{
  "@context": "http://iiif.io/api/presentation/2/context.json",
  "@id": "https://mejackreed.github.io/parker-scale-data/xr745mn3815/annos/canvas-285.json",
  "@type": "sc:AnnotationList",
  "resources": [
    {
      "@id": "4498da2bb4d77f9c191e8dceeb8ef33a",
      "@type": "oa:Annotation",
      "motivation": "sc:painting",
      "resource": {
        "@id": "2aa672dc30d5b283a729569d00d9ba73",
        "@type": "cnt:ContentAsText",
        "format": "text/plain",
        "chars": "Hello!",
        "language": "eng"
      },
      "on": "http://dms-data.stanford.edu/Parker/xr745mn3815/canvas/canvas-285#xywh=0,0,300,300"
    }
  ]
}