{
  "@context": "http://iiif.io/api/presentation/2/context.json",
  "@id": "https://mejackreed.github.io/parker-scale-data/gf460xj6913/annos/canvas-270.json",
  "@type": "sc:AnnotationList",
  "resources": [
    {
      "@id": "090f9623f451601aa19c733cbcdd0e5f",
      "@type": "oa:Annotation",
      "motivation": "sc:painting",
      "resource": {
        "@id": "1d7a458f2619f959ca8e34acb13115f1",
        "@type": "cnt:ContentAsText",
        "format": "text/plain",
        "chars": "Hello!",
        "language": "eng"
      },
      "on": "http://dms-data.stanford.edu/Parker/gf460xj6913/canvas/canvas-270#xywh=0,0,300,300"
    }
  ]
}