{
  "@context": "http://iiif.io/api/presentation/2/context.json",
  "@id": "https://mejackreed.github.io/parker-scale-data/bk144vn3835/annos/canvas-21.json",
  "@type": "sc:AnnotationList",
  "resources": [
    {
      "@id": "e492be83b2dcfce66e6ff4ced3e51f1e",
      "@type": "oa:Annotation",
      "motivation": "sc:painting",
      "resource": {
        "@id": "9fc45ef7c08e66cbf7bc6e7130c215bd",
        "@type": "cnt:ContentAsText",
        "format": "text/plain",
        "chars": "Hello!",
        "language": "eng"
      },
      "on": "http://dms-data.stanford.edu/Parker/bk144vn3835/canvas/canvas-21"
    }
  ]
}