{
  "@context": "http://iiif.io/api/presentation/2/context.json",
  "@id": "https://mejackreed.github.io/parker-scale-data/cr633rp5601/annos/canvas-81.json",
  "@type": "sc:AnnotationList",
  "resources": [
    {
      "@id": "83a65b5126e93d0aa5df9ea37653cc23",
      "@type": "oa:Annotation",
      "motivation": "sc:painting",
      "resource": {
        "@id": "7003aa75f9f5d60ca993d4e8b66d89cc",
        "@type": "cnt:ContentAsText",
        "format": "text/plain",
        "chars": "Hello!",
        "language": "eng"
      },
      "on": "http://dms-data.stanford.edu/Parker/cr633rp5601/canvas/canvas-81#xywh=0,0,300,300"
    }
  ]
}