{
  "@context": "http://iiif.io/api/presentation/2/context.json",
  "@id": "https://mejackreed.github.io/parker-scale-data/nd699vv5900/annos/canvas-606.json",
  "@type": "sc:AnnotationList",
  "resources": [
    {
      "@id": "887882b40f09c7b74e697c18e2bd31e5",
      "@type": "oa:Annotation",
      "motivation": "sc:painting",
      "resource": {
        "@id": "3afc1c8fde377d2115526faa20fcef38",
        "@type": "cnt:ContentAsText",
        "format": "text/plain",
        "chars": "Hello!",
        "language": "eng"
      },
      "on": "http://dms-data.stanford.edu/Parker/nd699vv5900/canvas/canvas-606#xywh=0,0,300,300"
    }
  ]
}