{
  "@context": "http://iiif.io/api/presentation/2/context.json",
  "@id": "https://mejackreed.github.io/parker-scale-data/bp218ym5464/annos/canvas-92.json",
  "@type": "sc:AnnotationList",
  "resources": [
    {
      "@id": "e362f139c9286efe886a7cc88004994c",
      "@type": "oa:Annotation",
      "motivation": "sc:painting",
      "resource": {
        "@id": "8ebb1dc50a9724b8ce72c827d4e1190d",
        "@type": "cnt:ContentAsText",
        "format": "text/plain",
        "chars": "Hello!",
        "language": "eng"
      },
      "on": "http://dms-data.stanford.edu/Parker/bp218ym5464/canvas/canvas-92#xywh=0,0,300,300"
    }
  ]
}