{
  "@context": "http://iiif.io/api/presentation/2/context.json",
  "@id": "https://mejackreed.github.io/parker-scale-data/vd280pd3953/annos/canvas-392.json",
  "@type": "sc:AnnotationList",
  "resources": [
    {
      "@id": "be9370ff02db4bb71e9b2fb3a396a371",
      "@type": "oa:Annotation",
      "motivation": "sc:painting",
      "resource": {
        "@id": "64f40ef1681a9f8a84afc79a23de42c8",
        "@type": "cnt:ContentAsText",
        "format": "text/plain",
        "chars": "Hello!",
        "language": "eng"
      },
      "on": "http://dms-data.stanford.edu/Parker/vd280pd3953/canvas/canvas-392#xywh=0,0,300,300"
    }
  ]
}