{
  "@context": "http://iiif.io/api/presentation/2/context.json",
  "@id": "https://mejackreed.github.io/parker-scale-data/vd280pd3953/annos/canvas-388.json",
  "@type": "sc:AnnotationList",
  "resources": [
    {
      "@id": "17c0031199a862bb0dc774c4ba400a6c",
      "@type": "oa:Annotation",
      "motivation": "sc:painting",
      "resource": {
        "@id": "63e58c0d1a4dfc177684e5815a801bc7",
        "@type": "cnt:ContentAsText",
        "format": "text/plain",
        "chars": "Hello!",
        "language": "eng"
      },
      "on": "http://dms-data.stanford.edu/Parker/vd280pd3953/canvas/canvas-388#xywh=0,0,300,300"
    }
  ]
}