{
  "@context": "http://iiif.io/api/presentation/2/context.json",
  "@id": "https://mejackreed.github.io/parker-scale-data/fr610kh2998/annos/canvas-1.json",
  "@type": "sc:AnnotationList",
  "resources": [
    {
      "@id": "033a436295a230bd27cbd80105badc8f",
      "@type": "oa:Annotation",
      "motivation": "sc:painting",
      "resource": {
        "@id": "9c52537ca75a717ae519aa4f5dc03ed4",
        "@type": "cnt:ContentAsText",
        "format": "text/plain",
        "chars": "Hello!",
        "language": "eng"
      },
      "on": "http://dms-data.stanford.edu/Parker/fr610kh2998/canvas/canvas-1#xywh=0,0,300,300"
    }
  ]
}