{
  "@context": "http://iiif.io/api/presentation/2/context.json",
  "@id": "https://mejackreed.github.io/parker-scale-data/gc974js8368/annos/canvas-2.json",
  "@type": "sc:AnnotationList",
  "resources": [
    {
      "@id": "b846926cecbd37d93d71f58fcbed973a",
      "@type": "oa:Annotation",
      "motivation": "sc:painting",
      "resource": {
        "@id": "ed151bb0d52d35ce62c0858e6d763939",
        "@type": "cnt:ContentAsText",
        "format": "text/plain",
        "chars": "Hello!",
        "language": "eng"
      },
      "on": "http://dms-data.stanford.edu/Parker/gc974js8368/canvas/canvas-2#xywh=0,0,300,300"
    }
  ]
}