{
  "@context": "http://iiif.io/api/presentation/2/context.json",
  "@id": "https://mejackreed.github.io/parker-scale-data/cz539hm0946/annos/canvas-155.json",
  "@type": "sc:AnnotationList",
  "resources": [
    {
      "@id": "cb348d821122a54163a064bf394faff8",
      "@type": "oa:Annotation",
      "motivation": "sc:painting",
      "resource": {
        "@id": "c11736814f46de8c5875896b7ce6f41b",
        "@type": "cnt:ContentAsText",
        "format": "text/plain",
        "chars": "Hello!",
        "language": "eng"
      },
      "on": "http://dms-data.stanford.edu/Parker/cz539hm0946/canvas/canvas-155#xywh=0,0,300,300"
    }
  ]
}