{
  "@context": "http://iiif.io/api/presentation/2/context.json",
  "@id": "https://mejackreed.github.io/parker-scale-data/vf742yx0561/annos/canvas-277.json",
  "@type": "sc:AnnotationList",
  "resources": [
    {
      "@id": "495a1b069500e2c9f261b20b2eeea566",
      "@type": "oa:Annotation",
      "motivation": "sc:painting",
      "resource": {
        "@id": "5f552784ad3271a507e0556de4f48059",
        "@type": "cnt:ContentAsText",
        "format": "text/plain",
        "chars": "Hello!",
        "language": "eng"
      },
      "on": "http://dms-data.stanford.edu/Parker/vf742yx0561/canvas/canvas-277#xywh=0,0,300,300"
    }
  ]
}