{
  "@context": "http://iiif.io/api/presentation/2/context.json",
  "@id": "https://mejackreed.github.io/parker-scale-data/sk095st1718/annos/canvas-118.json",
  "@type": "sc:AnnotationList",
  "resources": [
    {
      "@id": "70c6af0525400b71b27387d7805c706e",
      "@type": "oa:Annotation",
      "motivation": "sc:painting",
      "resource": {
        "@id": "0e752a55d05dd79925ac0587e9321ed9",
        "@type": "cnt:ContentAsText",
        "format": "text/plain",
        "chars": "Hello!",
        "language": "eng"
      },
      "on": "http://dms-data.stanford.edu/Parker/sk095st1718/canvas/canvas-118#xywh=0,0,300,300"
    }
  ]
}