{
  "@context": "http://iiif.io/api/presentation/2/context.json",
  "@id": "https://mejackreed.github.io/parker-scale-data/rf352tc5448/annos/canvas-271.json",
  "@type": "sc:AnnotationList",
  "resources": [
    {
      "@id": "b62d7f891bab9280bbcb0c4313f977d5",
      "@type": "oa:Annotation",
      "motivation": "sc:painting",
      "resource": {
        "@id": "57483a8beec69f580a94c8f1fc8dd13a",
        "@type": "cnt:ContentAsText",
        "format": "text/plain",
        "chars": "Hello!",
        "language": "eng"
      },
      "on": "https://dms-data.stanford.edu/Parker/rf352tc5448/canvas/canvas-271#xywh=0,0,300,300"
    }
  ]
}