{
  "@context": "http://iiif.io/api/presentation/2/context.json",
  "@id": "https://mejackreed.github.io/parker-scale-data/np697hc2819/annos/canvas-77.json",
  "@type": "sc:AnnotationList",
  "resources": [
    {
      "@id": "da19425668073c8e812871f15597f32d",
      "@type": "oa:Annotation",
      "motivation": "sc:painting",
      "resource": {
        "@id": "2d9b73f979e4bfef1bda76edcb6db538",
        "@type": "cnt:ContentAsText",
        "format": "text/plain",
        "chars": "Hello!",
        "language": "eng"
      },
      "on": "http://dms-data.stanford.edu/Parker/np697hc2819/canvas/canvas-77#xywh=0,0,300,300"
    }
  ]
}