{
  "@context": "http://iiif.io/api/presentation/2/context.json",
  "@id": "https://mejackreed.github.io/parker-scale-data/bc961dv0378/annos/canvas-63.json",
  "@type": "sc:AnnotationList",
  "resources": [
    {
      "@id": "35da939e7c40c0d9e96c7507188e84d4",
      "@type": "oa:Annotation",
      "motivation": "sc:painting",
      "resource": {
        "@id": "9db5955375c13f7da25fd0a3f68b923a",
        "@type": "cnt:ContentAsText",
        "format": "text/plain",
        "chars": "Hello!",
        "language": "eng"
      },
      "on": "http://dms-data.stanford.edu/Parker/bc961dv0378/canvas/canvas-63#xywh=0,0,300,300"
    }
  ]
}