{
  "@context": "http://iiif.io/api/presentation/2/context.json",
  "@id": "https://mejackreed.github.io/parker-scale-data/jd913tp1831/annos/canvas-119.json",
  "@type": "sc:AnnotationList",
  "resources": [
    {
      "@id": "c86334cc0b359014a3705c0681de263b",
      "@type": "oa:Annotation",
      "motivation": "sc:painting",
      "resource": {
        "@id": "a831b33e0800a78ca49fb61b2a56f07b",
        "@type": "cnt:ContentAsText",
        "format": "text/plain",
        "chars": "Hello!",
        "language": "eng"
      },
      "on": "http://dms-data.stanford.edu/Parker/jd913tp1831/canvas/canvas-119#xywh=0,0,300,300"
    }
  ]
}