{
  "@context": "http://iiif.io/api/presentation/2/context.json",
  "@id": "https://mejackreed.github.io/parker-scale-data/jd913tp1831/annos/canvas-316.json",
  "@type": "sc:AnnotationList",
  "resources": [
    {
      "@id": "72905b78418d298c3a7eaa1d53d1837a",
      "@type": "oa:Annotation",
      "motivation": "sc:painting",
      "resource": {
        "@id": "7b52819c78744d69e26da5f80ea8d900",
        "@type": "cnt:ContentAsText",
        "format": "text/plain",
        "chars": "Hello!",
        "language": "eng"
      },
      "on": "http://dms-data.stanford.edu/Parker/jd913tp1831/canvas/canvas-316#xywh=0,0,300,300"
    }
  ]
}