{
  "@context": "http://iiif.io/api/presentation/2/context.json",
  "@id": "https://mejackreed.github.io/parker-scale-data/dm805gn6112/annos/canvas-14.json",
  "@type": "sc:AnnotationList",
  "resources": [
    {
      "@id": "8d90f08a84b165dd8a70b3bb538bc6ec",
      "@type": "oa:Annotation",
      "motivation": "sc:painting",
      "resource": {
        "@id": "0e09c4b2e31b91ba40d5ed46ff584ee7",
        "@type": "cnt:ContentAsText",
        "format": "text/plain",
        "chars": "Hello!",
        "language": "eng"
      },
      "on": "http://dms-data.stanford.edu/Parker/dm805gn6112/canvas/canvas-14#xywh=0,0,300,300"
    }
  ]
}