{
  "@context": "http://iiif.io/api/presentation/2/context.json",
  "@id": "https://mejackreed.github.io/parker-scale-data/km029jy8838/annos/canvas-75.json",
  "@type": "sc:AnnotationList",
  "resources": [
    {
      "@id": "96f3aec8392e8dd0ff24fe1d5e636f5f",
      "@type": "oa:Annotation",
      "motivation": "sc:painting",
      "resource": {
        "@id": "fde526985b94ce2b89b1c42ab2ee0c08",
        "@type": "cnt:ContentAsText",
        "format": "text/plain",
        "chars": "Hello!",
        "language": "eng"
      },
      "on": "http://dms-data.stanford.edu/Parker/km029jy8838/canvas/canvas-76#xywh=0,0,300,300"
    }
  ]
}