{
  "@context": "http://iiif.io/api/presentation/2/context.json",
  "@id": "https://mejackreed.github.io/parker-scale-data/km029jy8838/annos/canvas-56.json",
  "@type": "sc:AnnotationList",
  "resources": [
    {
      "@id": "18187096309972b8d585b755b59485d8",
      "@type": "oa:Annotation",
      "motivation": "sc:painting",
      "resource": {
        "@id": "dfdd881cc1f2741b994c4ba297495d7b",
        "@type": "cnt:ContentAsText",
        "format": "text/plain",
        "chars": "Hello!",
        "language": "eng"
      },
      "on": "http://dms-data.stanford.edu/Parker/km029jy8838/canvas/canvas-57#xywh=0,0,300,300"
    }
  ]
}