{
  "@context": "http://iiif.io/api/presentation/2/context.json",
  "@id": "https://mejackreed.github.io/parker-scale-data/xs715gp9158/annos/canvas-25.json",
  "@type": "sc:AnnotationList",
  "resources": [
    {
      "@id": "ce9b872425c8638c8df754db4be1f338",
      "@type": "oa:Annotation",
      "motivation": "sc:painting",
      "resource": {
        "@id": "fb2d045fd7f0817a89bab52ca37abfe4",
        "@type": "cnt:ContentAsText",
        "format": "text/plain",
        "chars": "Hello!",
        "language": "eng"
      },
      "on": "http://dms-data.stanford.edu/Parker/xs715gp9158/canvas/canvas-25#xywh=0,0,300,300"
    }
  ]
}