{
  "@context": "http://iiif.io/api/presentation/2/context.json",
  "@id": "https://mejackreed.github.io/parker-scale-data/zh635rv2202/annos/canvas-242.json",
  "@type": "sc:AnnotationList",
  "resources": [
    {
      "@id": "decfde24e9dad1c0ba4877e93537f8a7",
      "@type": "oa:Annotation",
      "motivation": "sc:painting",
      "resource": {
        "@id": "cbc6fd603e477db92e5ec8b0a30194be",
        "@type": "cnt:ContentAsText",
        "format": "text/plain",
        "chars": "Hello!",
        "language": "eng"
      },
      "on": "http://dms-data.stanford.edu/Parker/zh635rv2202/canvas/canvas-242#xywh=0,0,300,300"
    }
  ]
}