{
  "@context": "http://iiif.io/api/presentation/2/context.json",
  "@id": "https://mejackreed.github.io/parker-scale-data/zx272hd6144/annos/canvas-546.json",
  "@type": "sc:AnnotationList",
  "resources": [
    {
      "@id": "2ad2e2295a1d0bc4b3d527cf7ffd0499",
      "@type": "oa:Annotation",
      "motivation": "sc:painting",
      "resource": {
        "@id": "3eb11816191bd1f850410ea3aa2763fc",
        "@type": "cnt:ContentAsText",
        "format": "text/plain",
        "chars": "Hello!",
        "language": "eng"
      },
      "on": "http://dms-data.stanford.edu/Parker/zx272hd6144/canvas/canvas-546#xywh=0,0,300,300"
    }
  ]
}