{
  "@context": "http://iiif.io/api/presentation/2/context.json",
  "@id": "https://mejackreed.github.io/parker-scale-data/bv488md1266/annos/canvas-37.json",
  "@type": "sc:AnnotationList",
  "resources": [
    {
      "@id": "59cd290d7292f52577c7f842e61f629d",
      "@type": "oa:Annotation",
      "motivation": "sc:painting",
      "resource": {
        "@id": "c04e66209f0aa9247716ba0f8e903d25",
        "@type": "cnt:ContentAsText",
        "format": "text/plain",
        "chars": "Hello!",
        "language": "eng"
      },
      "on": "http://dms-data.stanford.edu/Parker/bv488md1266/canvas/canvas-37#xywh=0,0,300,300"
    }
  ]
}