{
  "@context": "http://iiif.io/api/presentation/2/context.json",
  "@id": "https://mejackreed.github.io/parker-scale-data/bv488md1266/annos/canvas-384.json",
  "@type": "sc:AnnotationList",
  "resources": [
    {
      "@id": "9238ef18de7b073bafc8b9b68938e119",
      "@type": "oa:Annotation",
      "motivation": "sc:painting",
      "resource": {
        "@id": "c9f0d21b71ce2de9a7642e6c1238d319",
        "@type": "cnt:ContentAsText",
        "format": "text/plain",
        "chars": "Hello!",
        "language": "eng"
      },
      "on": "http://dms-data.stanford.edu/Parker/bv488md1266/canvas/canvas-384#xywh=0,0,300,300"
    }
  ]
}