{
  "@context": "http://iiif.io/api/presentation/2/context.json",
  "@id": "https://mejackreed.github.io/parker-scale-data/gx458ty6679/annos/canvas-409.json",
  "@type": "sc:AnnotationList",
  "resources": [
    {
      "@id": "4f8227b6078c5c00e37153dc33f47aba",
      "@type": "oa:Annotation",
      "motivation": "sc:painting",
      "resource": {
        "@id": "712f83b2e2dac95fdff8317e8c852cd2",
        "@type": "cnt:ContentAsText",
        "format": "text/plain",
        "chars": "Hello!",
        "language": "eng"
      },
      "on": "http://dms-data.stanford.edu/Parker/gx458ty6679/canvas/canvas-408#xywh=0,0,300,300"
    }
  ]
}