{
  "@context": "http://iiif.io/api/presentation/2/context.json",
  "@id": "https://mejackreed.github.io/parker-scale-data/md506kt8712/annos/canvas-17.json",
  "@type": "sc:AnnotationList",
  "resources": [
    {
      "@id": "fd626e0ec538e397350c5b068de2fbc3",
      "@type": "oa:Annotation",
      "motivation": "sc:painting",
      "resource": {
        "@id": "bbf553566951c9965e730bd6263a7f54",
        "@type": "cnt:ContentAsText",
        "format": "text/plain",
        "chars": "Hello!",
        "language": "eng"
      },
      "on": "http://dms-data.stanford.edu/Parker/md506kt8712/canvas/canvas-17#xywh=0,0,300,300"
    }
  ]
}