{
  "@context": "http://iiif.io/api/presentation/2/context.json",
  "@id": "https://mejackreed.github.io/parker-scale-data/xb003nj3345/annos/canvas-76.json",
  "@type": "sc:AnnotationList",
  "resources": [
    {
      "@id": "0626fbe3330569643b46a6fa89abd96d",
      "@type": "oa:Annotation",
      "motivation": "sc:painting",
      "resource": {
        "@id": "9091cbb51e3fb995bb6bbd9a5f3d3bec",
        "@type": "cnt:ContentAsText",
        "format": "text/plain",
        "chars": "Hello!",
        "language": "eng"
      },
      "on": "http://dms-data.stanford.edu/Parker/xb003nj3345/canvas/canvas-76#xywh=0,0,300,300"
    }
  ]
}