{
  "@context": "http://iiif.io/api/presentation/2/context.json",
  "@id": "https://mejackreed.github.io/parker-scale-data/vv924dt3892/annos/canvas-485.json",
  "@type": "sc:AnnotationList",
  "resources": [
    {
      "@id": "7af2161629fe6d5a0908676115c2ff29",
      "@type": "oa:Annotation",
      "motivation": "sc:painting",
      "resource": {
        "@id": "99a7f37f769b48433bce2a70c618a2ba",
        "@type": "cnt:ContentAsText",
        "format": "text/plain",
        "chars": "Hello!",
        "language": "eng"
      },
      "on": "http://dms-data.stanford.edu/Parker/vv924dt3892/canvas/canvas-485#xywh=0,0,300,300"
    }
  ]
}