{
  "@context": "http://iiif.io/api/presentation/2/context.json",
  "@id": "https://mejackreed.github.io/parker-scale-data/dg167rf3687/annos/canvas-55.json",
  "@type": "sc:AnnotationList",
  "resources": [
    {
      "@id": "bd2748072d102039182c9e7005b2d34e",
      "@type": "oa:Annotation",
      "motivation": "sc:painting",
      "resource": {
        "@id": "0e4503ca812df4d7c92dc87d8bf039f3",
        "@type": "cnt:ContentAsText",
        "format": "text/plain",
        "chars": "Hello!",
        "language": "eng"
      },
      "on": "http://dms-data.stanford.edu/Parker/dg167rf3687/canvas/canvas-55#xywh=0,0,300,300"
    }
  ]
}