{
  "@context": "http://iiif.io/api/presentation/2/context.json",
  "@id": "https://mejackreed.github.io/parker-scale-data/jj548nk9202/annos/canvas-274.json",
  "@type": "sc:AnnotationList",
  "resources": [
    {
      "@id": "47989d2b507f7b337d1882f7c8be05c6",
      "@type": "oa:Annotation",
      "motivation": "sc:painting",
      "resource": {
        "@id": "12ed010ec0aa9e8e98159710a67f59b9",
        "@type": "cnt:ContentAsText",
        "format": "text/plain",
        "chars": "Hello!",
        "language": "eng"
      },
      "on": "http://dms-data.stanford.edu/Parker/jj548nk9202/canvas/canvas-274#xywh=0,0,300,300"
    }
  ]
}