{
  "@context": "http://iiif.io/api/presentation/2/context.json",
  "@id": "https://mejackreed.github.io/parker-scale-data/jr282qg4527/annos/canvas-62.json",
  "@type": "sc:AnnotationList",
  "resources": [
    {
      "@id": "0bab401686258d30db62b6691cd38c5e",
      "@type": "oa:Annotation",
      "motivation": "sc:painting",
      "resource": {
        "@id": "f9a5a0755b2d4b70fa3271e69ea15225",
        "@type": "cnt:ContentAsText",
        "format": "text/plain",
        "chars": "Hello!",
        "language": "eng"
      },
      "on": "http://dms-data.stanford.edu/Parker/jr282qg4527/canvas/canvas-61#xywh=0,0,300,300"
    }
  ]
}