{
  "@context": "http://iiif.io/api/presentation/2/context.json",
  "@id": "https://mejackreed.github.io/parker-scale-data/yk983tq9075/annos/canvas-282.json",
  "@type": "sc:AnnotationList",
  "resources": [
    {
      "@id": "b0e22a02d51e43d8c4474d6a0b319043",
      "@type": "oa:Annotation",
      "motivation": "sc:painting",
      "resource": {
        "@id": "3311341e387bd3ae0bd7f8e09a83c2fa",
        "@type": "cnt:ContentAsText",
        "format": "text/plain",
        "chars": "Hello!",
        "language": "eng"
      },
      "on": "http://dms-data.stanford.edu/Parker/yk983tq9075/canvas/canvas-282#xywh=0,0,300,300"
    }
  ]
}