{
  "@context": "http://iiif.io/api/presentation/2/context.json",
  "@id": "https://mejackreed.github.io/parker-scale-data/vn460ct6671/annos/canvas-256.json",
  "@type": "sc:AnnotationList",
  "resources": [
    {
      "@id": "797ecd445e32d4a8a633f4011e19e646",
      "@type": "oa:Annotation",
      "motivation": "sc:painting",
      "resource": {
        "@id": "20ea25bad6a7dbd85b9874b0ec3b6eff",
        "@type": "cnt:ContentAsText",
        "format": "text/plain",
        "chars": "Hello!",
        "language": "eng"
      },
      "on": "http://dms-data.stanford.edu/Parker/vn460ct6671/canvas/canvas-256#xywh=0,0,300,300"
    }
  ]
}