{
  "@context": "http://iiif.io/api/presentation/2/context.json",
  "@id": "https://mejackreed.github.io/parker-scale-data/zs345bj2650/annos/canvas-227.json",
  "@type": "sc:AnnotationList",
  "resources": [
    {
      "@id": "83ca148530ad779b4d89783f1b4ec4cd",
      "@type": "oa:Annotation",
      "motivation": "sc:painting",
      "resource": {
        "@id": "823ccf3392c124f49cd2ce70ab617d08",
        "@type": "cnt:ContentAsText",
        "format": "text/plain",
        "chars": "Hello!",
        "language": "eng"
      },
      "on": "http://dms-data.stanford.edu/Parker/zs345bj2650/canvas/canvas-227#xywh=0,0,300,300"
    }
  ]
}