{
  "@context": "http://iiif.io/api/presentation/2/context.json",
  "@id": "https://mejackreed.github.io/parker-scale-data/gv751fq0828/annos/canvas-367.json",
  "@type": "sc:AnnotationList",
  "resources": [
    {
      "@id": "0948c2918e16ee2ca96b6241688646e5",
      "@type": "oa:Annotation",
      "motivation": "sc:painting",
      "resource": {
        "@id": "f048bd6e5309ae1682b6467d4d5d05f2",
        "@type": "cnt:ContentAsText",
        "format": "text/plain",
        "chars": "Hello!",
        "language": "eng"
      },
      "on": "http://dms-data.stanford.edu/Parker/gv751fq0828/canvas/canvas-367#xywh=0,0,300,300"
    }
  ]
}