{
  "@context": "http://iiif.io/api/presentation/2/context.json",
  "@id": "https://mejackreed.github.io/parker-scale-data/vx826tz1598/annos/canvas-81.json",
  "@type": "sc:AnnotationList",
  "resources": [
    {
      "@id": "b8486567831ae7f74567b8c191c92ba1",
      "@type": "oa:Annotation",
      "motivation": "sc:painting",
      "resource": {
        "@id": "8f9ba7f36c55e7439c2f6f4444417169",
        "@type": "cnt:ContentAsText",
        "format": "text/plain",
        "chars": "Hello!",
        "language": "eng"
      },
      "on": "http://dms-data.stanford.edu/Parker/vx826tz1598/canvas/canvas-81#xywh=0,0,300,300"
    }
  ]
}