{
  "@context": "http://iiif.io/api/presentation/2/context.json",
  "@id": "https://mejackreed.github.io/parker-scale-data/xk876dn8316/annos/canvas-514.json",
  "@type": "sc:AnnotationList",
  "resources": [
    {
      "@id": "4b0c9ce2f8dab1a679b9f7a4c50f46a8",
      "@type": "oa:Annotation",
      "motivation": "sc:painting",
      "resource": {
        "@id": "1825c2b3b54fb84bd732a626c4708229",
        "@type": "cnt:ContentAsText",
        "format": "text/plain",
        "chars": "Hello!",
        "language": "eng"
      },
      "on": "http://dms-data.stanford.edu/Parker/xk876dn8316/canvas/canvas-514#xywh=0,0,300,300"
    }
  ]
}