{
  "@context": "http://iiif.io/api/presentation/2/context.json",
  "@id": "https://mejackreed.github.io/parker-scale-data/wd305nz9008/annos/canvas-311.json",
  "@type": "sc:AnnotationList",
  "resources": [
    {
      "@id": "bf29fcbb0c237afda175c67d55546466",
      "@type": "oa:Annotation",
      "motivation": "sc:painting",
      "resource": {
        "@id": "4eb2d930669d2a7dfcb6a7821196cafc",
        "@type": "cnt:ContentAsText",
        "format": "text/plain",
        "chars": "Hello!",
        "language": "eng"
      },
      "on": "http://dms-data.stanford.edu/Parker/wd305nz9008/canvas/canvas-311#xywh=0,0,300,300"
    }
  ]
}