{
  "@context": "http://iiif.io/api/presentation/2/context.json",
  "@id": "https://mejackreed.github.io/parker-scale-data/fg493mp7832/annos/canvas-200.json",
  "@type": "sc:AnnotationList",
  "resources": [
    {
      "@id": "f2d5d9fdf2e8e9d6f46284954acda087",
      "@type": "oa:Annotation",
      "motivation": "sc:painting",
      "resource": {
        "@id": "23e3b1b170011c8ca3e99c7c4575a599",
        "@type": "cnt:ContentAsText",
        "format": "text/plain",
        "chars": "Hello!",
        "language": "eng"
      },
      "on": "http://dms-data.stanford.edu/Parker/fg493mp7832/canvas/canvas-200#xywh=0,0,300,300"
    }
  ]
}