{
  "@context": "http://iiif.io/api/presentation/2/context.json",
  "@id": "https://mejackreed.github.io/parker-scale-data/df920pp7276/annos/canvas-109.json",
  "@type": "sc:AnnotationList",
  "resources": [
    {
      "@id": "be96da532a04dce788877d3cd31b723c",
      "@type": "oa:Annotation",
      "motivation": "sc:painting",
      "resource": {
        "@id": "61f378d54b2a2c92ba4268bc0075bd85",
        "@type": "cnt:ContentAsText",
        "format": "text/plain",
        "chars": "Hello!",
        "language": "eng"
      },
      "on": "http://dms-data.stanford.edu/Parker/df920pp7276/canvas/canvas-109#xywh=0,0,300,300"
    }
  ]
}