{
  "@context": "http://iiif.io/api/presentation/2/context.json",
  "@id": "https://mejackreed.github.io/parker-scale-data/rs193jh6756/annos/canvas-177.json",
  "@type": "sc:AnnotationList",
  "resources": [
    {
      "@id": "b5239cfc2bddf5a7eacd70cbcec87716",
      "@type": "oa:Annotation",
      "motivation": "sc:painting",
      "resource": {
        "@id": "14971c8601a68785b3ea33a45c89080d",
        "@type": "cnt:ContentAsText",
        "format": "text/plain",
        "chars": "Hello!",
        "language": "eng"
      },
      "on": "http://dms-data.stanford.edu/Parker/rs193jh6756/canvas/canvas-177#xywh=0,0,300,300"
    }
  ]
}