{
  "@context": "http://iiif.io/api/presentation/2/context.json",
  "@id": "https://mejackreed.github.io/parker-scale-data/ks785nk0024/annos/canvas-128.json",
  "@type": "sc:AnnotationList",
  "resources": [
    {
      "@id": "a073b0477d0a9c996939eba2f03b0839",
      "@type": "oa:Annotation",
      "motivation": "sc:painting",
      "resource": {
        "@id": "79abf8536942b2fc5e13348b7425f25e",
        "@type": "cnt:ContentAsText",
        "format": "text/plain",
        "chars": "Hello!",
        "language": "eng"
      },
      "on": "http://dms-data.stanford.edu/Parker/ks785nk0024/canvas/canvas-128#xywh=0,0,300,300"
    }
  ]
}