{
  "@context": "http://iiif.io/api/presentation/2/context.json",
  "@id": "https://mejackreed.github.io/parker-scale-data/bj009wm8755/annos/canvas-438.json",
  "@type": "sc:AnnotationList",
  "resources": [
    {
      "@id": "3c049843054e53d2ec22cca537c4ed69",
      "@type": "oa:Annotation",
      "motivation": "sc:painting",
      "resource": {
        "@id": "46cde912f4396b4e8f9b561656f7ca81",
        "@type": "cnt:ContentAsText",
        "format": "text/plain",
        "chars": "Hello!",
        "language": "eng"
      },
      "on": "http://dms-data.stanford.edu/Parker/bj009wm8755/canvas/canvas-438"
    }
  ]
}