{
  "@context": "http://iiif.io/api/presentation/2/context.json",
  "@id": "https://mejackreed.github.io/parker-scale-data/bj009wm8755/annos/canvas-91.json",
  "@type": "sc:AnnotationList",
  "resources": [
    {
      "@id": "54c7f7e7ee88192624dfed656a6a0eec",
      "@type": "oa:Annotation",
      "motivation": "sc:painting",
      "resource": {
        "@id": "e4733b56dd527f5f75d3d19a85d50d54",
        "@type": "cnt:ContentAsText",
        "format": "text/plain",
        "chars": "Hello!",
        "language": "eng"
      },
      "on": "http://dms-data.stanford.edu/Parker/bj009wm8755/canvas/canvas-91"
    }
  ]
}