{
  "@context": "http://iiif.io/api/presentation/2/context.json",
  "@id": "https://mejackreed.github.io/parker-scale-data/bj009wm8755/annos/canvas-100.json",
  "@type": "sc:AnnotationList",
  "resources": [
    {
      "@id": "45863edd17989ddeaf4f6ef254526aea",
      "@type": "oa:Annotation",
      "motivation": "sc:painting",
      "resource": {
        "@id": "be8b85990e4a2bd7012ee04f55e1cafe",
        "@type": "cnt:ContentAsText",
        "format": "text/plain",
        "chars": "Hello!",
        "language": "eng"
      },
      "on": "http://dms-data.stanford.edu/Parker/bj009wm8755/canvas/canvas-100"
    }
  ]
}