{
  "@context": "http://iiif.io/api/presentation/2/context.json",
  "@id": "https://mejackreed.github.io/parker-scale-data/kh799ct7196/annos/canvas-526.json",
  "@type": "sc:AnnotationList",
  "resources": [
    {
      "@id": "13e0f9ebef463f2956e418d84f99e1a6",
      "@type": "oa:Annotation",
      "motivation": "sc:painting",
      "resource": {
        "@id": "14ae164e7a0fa6fe701f43b80e3fb955",
        "@type": "cnt:ContentAsText",
        "format": "text/plain",
        "chars": "Hello!",
        "language": "eng"
      },
      "on": "http://dms-data.stanford.edu/Parker/kh799ct7196/canvas/canvas-526#xywh=0,0,300,300"
    }
  ]
}