{
  "@context": "http://iiif.io/api/presentation/2/context.json",
  "@id": "https://mejackreed.github.io/parker-scale-data/pm669yz1553/annos/canvas-315.json",
  "@type": "sc:AnnotationList",
  "resources": [
    {
      "@id": "edb62e01544733579fd30d8dac2c6bc1",
      "@type": "oa:Annotation",
      "motivation": "sc:painting",
      "resource": {
        "@id": "1dabe65c3bd6a164b254f2c2096af017",
        "@type": "cnt:ContentAsText",
        "format": "text/plain",
        "chars": "Hello!",
        "language": "eng"
      },
      "on": "https://dms-data.stanford.edu/Parker/pm669yz1553/canvas/canvas-315#xywh=0,0,300,300"
    }
  ]
}