{
  "@context": "http://iiif.io/api/presentation/2/context.json",
  "@id": "https://mejackreed.github.io/parker-scale-data/fg385kv6407/annos/canvas-254.json",
  "@type": "sc:AnnotationList",
  "resources": [
    {
      "@id": "a9529000d06b649937073cfdb5c6b424",
      "@type": "oa:Annotation",
      "motivation": "sc:painting",
      "resource": {
        "@id": "5a1478d0c46f4e8f2938459d5f59832a",
        "@type": "cnt:ContentAsText",
        "format": "text/plain",
        "chars": "Hello!",
        "language": "eng"
      },
      "on": "http://dms-data.stanford.edu/Parker/fg385kv6407/canvas/canvas-254#xywh=0,0,300,300"
    }
  ]
}