{
  "@context": "http://iiif.io/api/presentation/2/context.json",
  "@id": "https://mejackreed.github.io/parker-scale-data/tt762jj7465/annos/canvas-37.json",
  "@type": "sc:AnnotationList",
  "resources": [
    {
      "@id": "3cb2b6f9ceeda1998abddd693991d515",
      "@type": "oa:Annotation",
      "motivation": "sc:painting",
      "resource": {
        "@id": "cfcadebf8c9a86a25cf76c87cecf3ddb",
        "@type": "cnt:ContentAsText",
        "format": "text/plain",
        "chars": "Hello!",
        "language": "eng"
      },
      "on": "http://dms-data.stanford.edu/Parker/tt762jj7465/canvas/canvas-37#xywh=0,0,300,300"
    }
  ]
}